{
	"id": "a.w",
	"description": "Deal Arts damage.",
	"action": "spray",
	"color": "#063970",
	"icon": "hidden",
	"maxAngleDiffInRevs": 0.01,
	"cooldown": 1200,
	"throttle": true,
	"name": "Night",
	"sound": "triplet",
	"movementProportionWhileChannelling": 1,
	"numProjectilesPerTick": 1,
	"intervalTicks": 1,
	"lengthTicks": 1,
	"effects": [],
	"jitterRatio": 2,
	"projectile": {
		"density": 0.0001,
		"ccd": true,
		"attractable": false,
		"linkable": false,
		"swappable": false,
		"radius": 0.0015,
		"spawnAtCursor": true,
		"speed": 0,
		"speedDecayPerTick": 0,
		"restitution": 0,
		"minTicks": 60,
		"maxTicks": 60,
		"hitInterval": 250,
		"damage": 0,
		"shieldTakesOwnership": false,
		"categories": 2,
		"selfPassthrough": true,
		"collideWith": 0,
		"expireOn": 0,
		"sound": "triplet",
		"color": "#063970",
		"renderers": [],
		"lifeSteal": 0,
		"behaviours": [
			{
				"type": "accelerate",
				"maxSpeed": 40,
				"accelerationPerSecond": -2
			},
			{
				"type": "spawn",
				"expire": true,
				"numProjectiles": 4,
				"trigger": {
					"expire": true
				},
				"spread": 0.75,
				"projectile": {
					"density": 0.0001,
					"ccd": true,
					"attractable": false,
					"linkable": false,
					"swappable": false,
					"radius": 0.0025,
					"speed": 3,
					"speedDecayPerTick": 0,
					"restitution": 0,
					"minTicks": 10,
					"maxTicks": 10,
					"hitInterval": 250,
					"damage": 0,
					"shieldTakesOwnership": false,
					"categories": 2,
					"selfPassthrough": true,
					"collideWith": 0,
					"sensor": true,
					"expireOn": 0,
					"sound": "triplet",
					"color": "#063970",
					"renderers": [],
					"lifeSteal": 0,
					"behaviours": [
						{
							"type": "accelerate",
							"maxSpeed": 40,
							"accelerationPerSecond": -1
						},
						{
							"type": "spawn",
							"expire": true,
							"numProjectiles": 4,
							"trigger": {
								"expire": true
							},
							"spread": 0.75,
							"projectile": {
								"density": 0.0001,
								"ccd": true,
								"attractable": false,
								"linkable": false,
								"swappable": false,
								"radius": 0.0025,
								"speed": 3,
								"speedDecayPerTick": 0,
								"restitution": 0,
								"minTicks": 10,
								"maxTicks": 10,
								"hitInterval": 250,
								"damage": 0,
								"shieldTakesOwnership": false,
								"categories": 2,
								"selfPassthrough": true,
								"collideWith": 0,
								"sensor": true,
								"expireOn": 0,
								"sound": "triplet",
								"color": "#063970",
								"renderers": [],
								"lifeSteal": 0,
								"behaviours": [
									{
										"type": "accelerate",
										"maxSpeed": 40,
										"accelerationPerSecond": -1
									},
									{
										"type": "spawn",
										"expire": true,
										"numProjectiles": 4,
										"trigger": {
											"expire": true
										},
										"spread": 0.75,
										"projectile": {
											"density": 0.0001,
											"ccd": true,
											"attractable": false,
											"linkable": false,
											"swappable": false,
											"radius": 0.0025,
											"speed": 0.9,
											"restitution": 0,
											"minTicks": 120,
											"maxTicks": 120,
											"hitInterval": 250,
											"damage": 0,
											"shieldTakesOwnership": false,
											"categories": 2,
											"selfPassthrough": true,
											"collideWith": 0,
											"sensor": true,
											"expireOn": 0,
											"sound": "triplet",
											"color": "#063970",
											"renderers": [
												{
													"type": "reticule",
													"color": "#063970",
													"radius": 0.04,
													"startingTicks": 60,
													"shrinkTicks": 60,
													"minRadius": 0.0375
												}
											],
											"lifeSteal": 0,
											"behaviours": [
												{
													"type": "homing",
													"afterTicks": 5,
													"targetType": "self",
													"newSpeed": 0
												},
												{
													"type": "spawn",
													"expire": true,
													"numProjectiles":8,
													"trigger": {
														"expire": true
													},
													"spread": 0.875,
													"projectile": {
														"density": 0.0001,
														"ccd": true,
														"attractable": false,
														"linkable": false,
														"swappable": false,
														"radius": 0.0025,
														"speed": 3,
														"speedDecayPerTick": 0,
														"restitution": 0,
														"minTicks": 90,
														"maxTicks": 90,
														"hitInterval": 250,
														"damage": 0,
														"shieldTakesOwnership": false,
														"categories": 2,
														"selfPassthrough": true,
														"collideWith": 1,
														"sensor": true,
														"expireOn": 0,
														"sound": "triplet",
														"color": "#063970aa",
														"renderers": [
															{
																"type": "ray",
																"ticks": 25,
																"vanish": 1,
																"light": 1
															}
														],
														"lifeSteal": 0,
														"behaviours": [],
														"soundHit": "standard",
														"buffs": [
															{
																"type": "burn",
																"hitInterval": 1,
																"maxTicks": 1,
																"packet": {
																	"source": "arts",
																	"lifeSteal": 0,
																	"damage": 4,
																	"noHit": true
																}
															}
														]
													}
												},
												{
													"type": "spawn",
													"numProjectiles": 8,
													"spread": 0.875,
													"trigger": {
														"afterTicks": 5
													},
													"projectile": {
														"density": 0.0001,
														"ccd": true,
														"attractable": false,
														"linkable": false,
														"swappable": false,
														"radius": 0.0025,
														"speed": 9,
														"speedDecayPerTick": 0,
														"restitution": 0,
														"minTicks": 10,
														"maxTicks": 10,
														"hitInterval": 250,
														"damage": 0,
														"shieldTakesOwnership": false,
														"categories": 2,
														"selfPassthrough": true,
														"collideWith": 0,
														"expireOn": 0,
														"sound": "triplet",
														"color": "#063970aa",
														"renderers": [
															{
																"type": "ray",
																"ticks": 120,
																"vanish": 1,
																"light": 0.3
															}
														],
														"lifeSteal": 0,
														"behaviours": [],
														"soundHit": "standard",
														"buffs": []
													}
												}
											],
											"soundHit": "standard",
											"buffs": []
										}
									}
								],
								"soundHit": "standard",
								"buffs": []
							}
						}
					],
					"soundHit": "standard",
					"buffs": []
				}
			}
		],
		"soundHit": "standard",
		"buffs": []
	}
}