{
	"density": 50,
	"radius": 0.003,
	"speed": 0.1,
	"collideWith": 65527,
	"maxTicks": 600,
	"damage": 0,
	"lifeSteal": 0,
	"categories": 3,
	"sound": "fireball",
	"expireOn": 0,
	"soundHit": "standard",
	"color": "#bfef45",
	"buffs": [],
	"behaviours": [
		{
			"type": "attract",
			"collideLike": 3,
			"categories": 2,
			"against": 12,
			"radius": 0.06,
			"accelerationPerTick": 0.4,
			"clampSpeed": 0.8
		},
		{
			"type": "attract",
			"collideLike": 3,
			"categories": 2,
			"against": 12,
			"radius": 0.04,
			"accelerationPerTick": 0.8,
			"clampSpeed": 0.1
		},
		{
			"type": "spawn",
			"triggers": [
				{
					"type": "collideWith",
					"collideWith": 65535,
					"against": 12,
					"triggerInterval": 4,
					"maxHits": 1000
				}
			],
			"projectile": {
				"density": 30,
				"radius": 0.06,
				"selfPassthrough": true,
				"speed": 0,
				"maxTicks": 10,
				"sense": 1,
				"collideWith": 0,
				"damage": 0,
				"expireOn": 0,
				"lifeSteal": 0,
				"categories": 2,
				"sound": "fireball",
				"soundHit": "standard",
				"color": "#bfef45",
				"buffs": [
					{
						"type": "burn",
						"hitInterval": 1,
						"maxTicks": 1,
						"packet": {
							"source": "arts",
							"lifeSteal": 0,
							"damage": 10
						}
					}
				],
				"behaviours": [],
				"renderers": [
					{
						"type": "projectile",
						"color": "#bfef4511",
						"ticks": 40
					}
				]
			}
		}
	],
	"renderers": [
		{
			"type": "projectile",
			"ticks": 10
		},
		{
			"type": "reticule",
			"radius": 0.06,
			"minRadius": 0.059,
			"color": "#bfef4522"
		}
	]

}